CHANGES.rst
DESCRIPTION.rst
LICENSE
MANIFEST.in
README.md
setup.py
src/wai.annotations.yolo.egg-info/PKG-INFO
src/wai.annotations.yolo.egg-info/SOURCES.txt
src/wai.annotations.yolo.egg-info/dependency_links.txt
src/wai.annotations.yolo.egg-info/entry_points.txt
src/wai.annotations.yolo.egg-info/namespace_packages.txt
src/wai.annotations.yolo.egg-info/requires.txt
src/wai.annotations.yolo.egg-info/top_level.txt
src/wai/annotations/yolo/__init__.py
src/wai/annotations/yolo/od/__init__.py
src/wai/annotations/yolo/od/_format.py
src/wai/annotations/yolo/od/component/_FromYOLOOD.py
src/wai/annotations/yolo/od/component/_ToYOLOOD.py
src/wai/annotations/yolo/od/component/_YOLOODReader.py
src/wai/annotations/yolo/od/component/_YOLOODWriter.py
src/wai/annotations/yolo/od/component/__init__.py
src/wai/annotations/yolo/od/specifier/_YOLOODInputFormatSpecifier.py
src/wai/annotations/yolo/od/specifier/_YOLOODOutputFormatSpecifier.py
src/wai/annotations/yolo/od/specifier/__init__.py